setup.cfg
setup.py
linie/__init__.py
linie/exceptions.py
linie/handlers.py
linie/loggers.py
linie.egg-info/PKG-INFO
linie.egg-info/SOURCES.txt
linie.egg-info/dependency_links.txt
linie.egg-info/top_level.txt