Metadata-Version: 1.1
Name: linie
Version: 0.0.0-dev1
Summary: Logging utilities.
Home-page: https://github.com/Dinoshauer/linie
Author: Kasper Jacobsen
Author-email: k@mackwerk.dk
License: MIT
Platform: UNKNOWN
Classifier: License :: OSI Approved :: MIT License
